CHANGES.rst
DESCRIPTION.rst
MANIFEST.in
README.md
setup.py
src/wai.tflite_model_maker.egg-info/PKG-INFO
src/wai.tflite_model_maker.egg-info/SOURCES.txt
src/wai.tflite_model_maker.egg-info/dependency_links.txt
src/wai.tflite_model_maker.egg-info/entry_points.txt
src/wai.tflite_model_maker.egg-info/namespace_packages.txt
src/wai.tflite_model_maker.egg-info/requires.txt
src/wai.tflite_model_maker.egg-info/top_level.txt
src/wai/tmm/__init__.py
src/wai/tmm/blah.py
src/wai/tmm/blah3.py
src/wai/tmm/common/__init__.py
src/wai/tmm/common/hyper.py
src/wai/tmm/common/io.py
src/wai/tmm/common/optimize.py
src/wai/tmm/common/predict_utils.py
src/wai/tmm/imgcls/__init__.py
src/wai/tmm/imgcls/predict.py
src/wai/tmm/imgcls/predict_poll.py
src/wai/tmm/imgcls/predict_redis.py
src/wai/tmm/imgcls/predict_utils.py
src/wai/tmm/imgcls/train.py
src/wai/tmm/objdet/__init__.py
src/wai/tmm/objdet/predict.py
src/wai/tmm/objdet/predict_poll.py
src/wai/tmm/objdet/predict_redis.py
src/wai/tmm/objdet/predict_utils.py
src/wai/tmm/objdet/train.py