Metadata-Version: 1.1
Name: wai.tflite-model-maker
Version: 0.0.4
Summary: tflite model maker command-line utilities.
Home-page: https://github.com/waikato-datamining/tensorflow/tree/master/tflite_model_maker
Author: Peter Reutemann and TensorFlow Team
Author-email: fracpete@waikato.ac.nz
License: Apache 2.0 License
Platform: UNKNOWN
Classifier: Development Status :: 4 - Beta
Classifier: License :: OSI Approved :: Apache Software License
Classifier: Topic :: Scientific/Engineering :: Artificial Intelligence
Classifier: Programming Language :: Python :: 3
